{
  "platform": "react",
  "code": {
    "lang": "ts",
    "scheme": "blackbox",
    "reactRuntime": "classic"
  },
  "style": {
    "scheme": "css-modules",
    "defaultStyleCssFilePath": "plasmic/plasmic__default_style.css"
  },
  "images": {
    "scheme": "inlined",
    "publicDir": "../public",
    "publicUrlPrefix": "/static/"
  },
  "tokens": {
    "scheme": "theo",
    "tokensFilePath": "plasmic-tokens.theo.json"
  },
  "srcDir": "src/components",
  "defaultPlasmicDir": "./plasmic",
  "projects": [
    {
      "projectId": "seaQhLVS4bbjiGvJJrRwyL",
      "projectApiToken": "nPw276qGsy9kISQCHrcRrsj3Y9Yva9TMyYKNUpoOMOHgRj1A51qOC6LMB2185QlA52K87n32oQJHSi5be9w",
      "projectName": "LIBRARY Plasmic Color + Type",
      "version": ">0.0.0",
      "cssFilePath": "plasmic/library_plasmic_color_type/plasmic.module.css",
      "components": [],
      "icons": [],
      "images": [],
      "indirect": true,
      "globalContextsFilePath": "",
      "splitsProviderFilePath": "",
      "styleTokensProviderFilePath": "plasmic/library_plasmic_color_type/PlasmicStyleTokensProvider.tsx",
      "projectModuleFilePath": "plasmic/library_plasmic_color_type/plasmic.tsx",
      "codeComponents": [],
      "customFunctions": []
    },
    {
      "projectId": "bCHRxdj8eN21PNzfM9AohB",
      "projectApiToken": "mrYlUaPqe7bWAXvBcuQOWEiO28vmDlqeMEJT5TeE78i0faSnh1xGj3qnw6DnWCvnnOAL5dnzYXimJP7S0A",
      "projectName": "Simple Light Landing Page",
      "version": "latest",
      "cssFilePath": "plasmic/simple_light_landing_page/plasmic.module.css",
      "components": [
        {
          "id": "hGve5AOfkFjw",
          "name": "Home",
          "type": "managed",
          "projectId": "bCHRxdj8eN21PNzfM9AohB",
          "renderModuleFilePath": "plasmic/simple_light_landing_page/PlasmicHome.tsx",
          "importSpec": {
            "modulePath": "Home.tsx"
          },
          "cssFilePath": "plasmic/simple_light_landing_page/PlasmicHome.module.css",
          "scheme": "blackbox",
          "componentType": "page",
          "path": "/"
        },
        {
          "id": "BzxOGjPiACbD",
          "name": "Header",
          "type": "managed",
          "projectId": "bCHRxdj8eN21PNzfM9AohB",
          "renderModuleFilePath": "plasmic/simple_light_landing_page/PlasmicHeader.tsx",
          "importSpec": {
            "modulePath": "Header.tsx"
          },
          "cssFilePath": "plasmic/simple_light_landing_page/PlasmicHeader.module.css",
          "scheme": "blackbox",
          "componentType": "component"
        },
        {
          "id": "YccH37mR_3eT",
          "name": "Footer",
          "type": "managed",
          "projectId": "bCHRxdj8eN21PNzfM9AohB",
          "renderModuleFilePath": "plasmic/simple_light_landing_page/PlasmicFooter.tsx",
          "importSpec": {
            "modulePath": "Footer.tsx"
          },
          "cssFilePath": "plasmic/simple_light_landing_page/PlasmicFooter.module.css",
          "scheme": "blackbox",
          "componentType": "component"
        },
        {
          "id": "YYMcqSJLTk6R",
          "name": "FeatureCard",
          "type": "managed",
          "projectId": "bCHRxdj8eN21PNzfM9AohB",
          "renderModuleFilePath": "plasmic/simple_light_landing_page/PlasmicFeatureCard.tsx",
          "importSpec": {
            "modulePath": "FeatureCard.tsx"
          },
          "cssFilePath": "plasmic/simple_light_landing_page/PlasmicFeatureCard.module.css",
          "scheme": "blackbox",
          "componentType": "component"
        },
        {
          "id": "DW2DDj_kTyOA",
          "name": "HomeCta",
          "type": "managed",
          "projectId": "bCHRxdj8eN21PNzfM9AohB",
          "renderModuleFilePath": "plasmic/simple_light_landing_page/PlasmicHomeCta.tsx",
          "importSpec": {
            "modulePath": "HomeCta.tsx"
          },
          "cssFilePath": "plasmic/simple_light_landing_page/PlasmicHomeCta.module.css",
          "scheme": "blackbox",
          "componentType": "component"
        },
        {
          "id": "TlImO_t-NXKC",
          "name": "IconLink",
          "type": "managed",
          "projectId": "bCHRxdj8eN21PNzfM9AohB",
          "renderModuleFilePath": "plasmic/simple_light_landing_page/PlasmicIconLink.tsx",
          "importSpec": {
            "modulePath": "IconLink.tsx"
          },
          "cssFilePath": "plasmic/simple_light_landing_page/PlasmicIconLink.module.css",
          "scheme": "blackbox",
          "componentType": "component"
        },
        {
          "id": "HS9HmUY-zvMo",
          "name": "Testimonial",
          "type": "managed",
          "projectId": "bCHRxdj8eN21PNzfM9AohB",
          "renderModuleFilePath": "plasmic/simple_light_landing_page/PlasmicTestimonial.tsx",
          "importSpec": {
            "modulePath": "Testimonial.tsx"
          },
          "cssFilePath": "plasmic/simple_light_landing_page/PlasmicTestimonial.module.css",
          "scheme": "blackbox",
          "componentType": "component"
        },
        {
          "id": "VTHj1Tv6HVd5",
          "name": "Avatar",
          "type": "managed",
          "projectId": "bCHRxdj8eN21PNzfM9AohB",
          "renderModuleFilePath": "plasmic/simple_light_landing_page/PlasmicAvatar.tsx",
          "importSpec": {
            "modulePath": "Avatar.tsx"
          },
          "cssFilePath": "plasmic/simple_light_landing_page/PlasmicAvatar.module.css",
          "scheme": "blackbox",
          "componentType": "component"
        },
        {
          "id": "N98xJ3Xnx-EM",
          "name": "Pricing",
          "type": "managed",
          "projectId": "bCHRxdj8eN21PNzfM9AohB",
          "renderModuleFilePath": "plasmic/simple_light_landing_page/PlasmicPricing.tsx",
          "importSpec": {
            "modulePath": "Pricing.tsx"
          },
          "cssFilePath": "plasmic/simple_light_landing_page/PlasmicPricing.module.css",
          "scheme": "blackbox",
          "componentType": "page",
          "path": "/pricing"
        },
        {
          "id": "FLq7eexFTSYZ",
          "name": "BaseCard",
          "type": "managed",
          "projectId": "bCHRxdj8eN21PNzfM9AohB",
          "renderModuleFilePath": "plasmic/simple_light_landing_page/PlasmicBaseCard.tsx",
          "importSpec": {
            "modulePath": "BaseCard.tsx"
          },
          "cssFilePath": "plasmic/simple_light_landing_page/PlasmicBaseCard.module.css",
          "scheme": "blackbox",
          "componentType": "component"
        },
        {
          "id": "5cRJRi3LWFl_",
          "name": "Plan",
          "type": "managed",
          "projectId": "bCHRxdj8eN21PNzfM9AohB",
          "renderModuleFilePath": "plasmic/simple_light_landing_page/PlasmicPlan.tsx",
          "importSpec": {
            "modulePath": "Plan.tsx"
          },
          "cssFilePath": "plasmic/simple_light_landing_page/PlasmicPlan.module.css",
          "scheme": "blackbox",
          "componentType": "component"
        },
        {
          "id": "OTvwM5e840hh",
          "name": "Bullet",
          "type": "managed",
          "projectId": "bCHRxdj8eN21PNzfM9AohB",
          "renderModuleFilePath": "plasmic/simple_light_landing_page/PlasmicBullet.tsx",
          "importSpec": {
            "modulePath": "Bullet.tsx"
          },
          "cssFilePath": "plasmic/simple_light_landing_page/PlasmicBullet.module.css",
          "scheme": "blackbox",
          "componentType": "component"
        },
        {
          "id": "dGMYSpLdGiXW",
          "name": "Faq",
          "type": "managed",
          "projectId": "bCHRxdj8eN21PNzfM9AohB",
          "renderModuleFilePath": "plasmic/simple_light_landing_page/PlasmicFaq.tsx",
          "importSpec": {
            "modulePath": "Faq.tsx"
          },
          "cssFilePath": "plasmic/simple_light_landing_page/PlasmicFaq.module.css",
          "scheme": "blackbox",
          "componentType": "component"
        },
        {
          "id": "rI6svspZhmSr",
          "name": "Features",
          "type": "managed",
          "projectId": "bCHRxdj8eN21PNzfM9AohB",
          "renderModuleFilePath": "plasmic/simple_light_landing_page/PlasmicFeatures.tsx",
          "importSpec": {
            "modulePath": "Features.tsx"
          },
          "cssFilePath": "plasmic/simple_light_landing_page/PlasmicFeatures.module.css",
          "scheme": "blackbox",
          "componentType": "page",
          "path": "/features"
        },
        {
          "id": "4q1n_5EvVPGF",
          "name": "Section",
          "type": "managed",
          "projectId": "bCHRxdj8eN21PNzfM9AohB",
          "renderModuleFilePath": "plasmic/simple_light_landing_page/PlasmicSection.tsx",
          "importSpec": {
            "modulePath": "Section.tsx"
          },
          "cssFilePath": "plasmic/simple_light_landing_page/PlasmicSection.module.css",
          "scheme": "blackbox",
          "componentType": "component"
        },
        {
          "id": "w69dEWwqNjuK",
          "name": "Button",
          "type": "managed",
          "projectId": "bCHRxdj8eN21PNzfM9AohB",
          "renderModuleFilePath": "plasmic/simple_light_landing_page/PlasmicButton.tsx",
          "importSpec": {
            "modulePath": "Button.tsx"
          },
          "cssFilePath": "plasmic/simple_light_landing_page/PlasmicButton.module.css",
          "scheme": "blackbox",
          "componentType": "component",
          "plumeType": "button"
        },
        {
          "id": "hV88TT7qSqn4",
          "name": "TextInput",
          "type": "managed",
          "projectId": "bCHRxdj8eN21PNzfM9AohB",
          "renderModuleFilePath": "plasmic/simple_light_landing_page/PlasmicTextInput.tsx",
          "importSpec": {
            "modulePath": "TextInput.tsx"
          },
          "cssFilePath": "plasmic/simple_light_landing_page/PlasmicTextInput.module.css",
          "scheme": "blackbox",
          "componentType": "component",
          "plumeType": "text-input"
        }
      ],
      "icons": [
        {
          "id": "GBbKlDMQeRfq",
          "name": "TwitterIconIcon",
          "moduleFilePath": "plasmic/simple_light_landing_page/icons/PlasmicIcon__TwitterIcon.tsx"
        },
        {
          "id": "JL8YjQPpR527",
          "name": "GithubIconIcon",
          "moduleFilePath": "plasmic/simple_light_landing_page/icons/PlasmicIcon__GithubIcon.tsx"
        },
        {
          "id": "97Xk6b1OrE_F",
          "name": "FacebookIconIcon",
          "moduleFilePath": "plasmic/simple_light_landing_page/icons/PlasmicIcon__FacebookIcon.tsx"
        },
        {
          "id": "Mu2JSUzMo_Jx",
          "name": "FacebookLogoIcon",
          "moduleFilePath": "plasmic/simple_light_landing_page/icons/PlasmicIcon__FacebookLogo.tsx"
        },
        {
          "id": "zZn6qT5NR0bY",
          "name": "LogoIcon",
          "moduleFilePath": "plasmic/simple_light_landing_page/icons/PlasmicIcon__Logo.tsx"
        },
        {
          "id": "CHglFvfdOYYj",
          "name": "SphereIcon",
          "moduleFilePath": "plasmic/simple_light_landing_page/icons/PlasmicIcon__Sphere.tsx"
        },
        {
          "id": "1ZCYZMdjey0w",
          "name": "QuoteDashesIcon",
          "moduleFilePath": "plasmic/simple_light_landing_page/icons/PlasmicIcon__QuoteDashes.tsx"
        },
        {
          "id": "Xt67GNzMzr04",
          "name": "TinderLogoIcon",
          "moduleFilePath": "plasmic/simple_light_landing_page/icons/PlasmicIcon__TinderLogo.tsx"
        },
        {
          "id": "h6iDLxKJpvP5",
          "name": "AirbnbLogoIcon",
          "moduleFilePath": "plasmic/simple_light_landing_page/icons/PlasmicIcon__AirbnbLogo.tsx"
        },
        {
          "id": "2TrXU8JKmCUI",
          "name": "HubspotLogoIcon",
          "moduleFilePath": "plasmic/simple_light_landing_page/icons/PlasmicIcon__HubspotLogo.tsx"
        },
        {
          "id": "9QdYwl9PjvMK",
          "name": "AmazonLogoIcon",
          "moduleFilePath": "plasmic/simple_light_landing_page/icons/PlasmicIcon__AmazonLogo.tsx"
        },
        {
          "id": "29S5G4T0Xglv",
          "name": "SwapIcon",
          "moduleFilePath": "plasmic/simple_light_landing_page/icons/PlasmicIcon__Swap.tsx"
        },
        {
          "id": "LlzyTWmJQnBm",
          "name": "SlotIcon",
          "moduleFilePath": "plasmic/simple_light_landing_page/icons/PlasmicIcon__Slot.tsx"
        },
        {
          "id": "0frAsW3dxtgG",
          "name": "CycleIcon",
          "moduleFilePath": "plasmic/simple_light_landing_page/icons/PlasmicIcon__Cycle.tsx"
        },
        {
          "id": "a7-Zhqz50qF-",
          "name": "HammerIcon",
          "moduleFilePath": "plasmic/simple_light_landing_page/icons/PlasmicIcon__Hammer.tsx"
        },
        {
          "id": "G-33Gu15e5-Z",
          "name": "PencilIcon",
          "moduleFilePath": "plasmic/simple_light_landing_page/icons/PlasmicIcon__Pencil.tsx"
        },
        {
          "id": "qxlr1oCs9DrX",
          "name": "LightningIcon",
          "moduleFilePath": "plasmic/simple_light_landing_page/icons/PlasmicIcon__Lightning.tsx"
        },
        {
          "id": "RUD0lWwcI_qm",
          "name": "RightArrowIcon",
          "moduleFilePath": "plasmic/simple_light_landing_page/icons/PlasmicIcon__RightArrow.tsx"
        },
        {
          "id": "Br5GbqsMY81v",
          "name": "Done24PxSvg2Icon",
          "moduleFilePath": "plasmic/simple_light_landing_page/icons/PlasmicIcon__Done24PxSvg2.tsx"
        },
        {
          "id": "WfT4K3HE86Ez",
          "name": "IconIcon",
          "moduleFilePath": "plasmic/simple_light_landing_page/icons/PlasmicIcon__Icon.tsx"
        },
        {
          "id": "4nvAXuIc7Qf6",
          "name": "CheckSvgIcon",
          "moduleFilePath": "plasmic/simple_light_landing_page/icons/PlasmicIcon__CheckSvg.tsx"
        },
        {
          "id": "eTSWyKDD7ZNa",
          "name": "SearchSvgIcon",
          "moduleFilePath": "plasmic/simple_light_landing_page/icons/PlasmicIcon__SearchSvg.tsx"
        }
      ],
      "images": [
        {
          "id": "tofw42u7HQqE",
          "name": "profilepic",
          "filePath": "plasmic/simple_light_landing_page/images/profilepic.png"
        },
        {
          "id": "sIhHDXksyZoZ",
          "name": "task",
          "filePath": "plasmic/simple_light_landing_page/images/task.png"
        },
        {
          "id": "cLyt2igCF_CA",
          "name": "simple-project",
          "filePath": "plasmic/simple_light_landing_page/images/simpleProject.png"
        },
        {
          "id": "J7FpxGVoYHX2",
          "name": "hero-image",
          "filePath": "plasmic/simple_light_landing_page/images/heroImage.png"
        }
      ],
      "indirect": false,
      "globalContextsFilePath": "",
      "splitsProviderFilePath": "",
      "styleTokensProviderFilePath": "plasmic/simple_light_landing_page/PlasmicStyleTokensProvider.tsx",
      "projectModuleFilePath": "plasmic/simple_light_landing_page/plasmic.tsx",
      "codeComponents": [
        {
          "id": "EJvdgseGK8D6",
          "name": "PlasmicHead",
          "displayName": "hostless-plasmic-head",
          "componentImportPath": "@plasmicapp/react-web"
        },
        {
          "id": "Tmz6C-q3CHNA",
          "name": "Fetcher",
          "displayName": "plasmic-data-source-fetcher",
          "componentImportPath": "@plasmicapp/react-web/lib/data-sources"
        }
      ],
      "customFunctions": []
    }
  ],
  "globalVariants": {
    "variantGroups": [
      {
        "id": "JgaY4LQzArdv",
        "name": "Screen",
        "projectId": "bCHRxdj8eN21PNzfM9AohB",
        "contextFilePath": "plasmic/simple_light_landing_page/PlasmicGlobalVariant__Screen.tsx"
      }
    ]
  },
  "wrapPagesWithGlobalContexts": true,
  "cliVersion": "0.1.342",
  "$schema": "https://unpkg.com/@plasmicapp/cli@0.1.342/dist/plasmic.schema.json"
}
